objxp/__init__.py
objxp/__main__.py
objxp-1.0.4.dist-info/licenses/LICENSE
objxp-1.0.4.dist-info/METADATA
objxp-1.0.4.dist-info/WHEEL
objxp-1.0.4.dist-info/entry_points.txt
objxp-1.0.4.dist-info/top_level.txt
objxp-1.0.4.dist-info/RECORD
