Metadata-Version: 2.4
Name: objxp
Version: 1.0.4
Summary: List the members in a Object[also Class or Module].
Author-email: lukelin <hongfoo@foxmail.com>
License: Mozilla Public License Version 2.0
Project-URL: Homepage, https://github.com/sunrenn/objxp
Keywords: dir,vars,debug
Classifier: License :: OSI Approved :: MIT License
Classifier: Programming Language :: Python
Classifier: Programming Language :: Python :: 3
Classifier: Development Status :: 4 - Beta
Classifier: Environment :: Win32 (MS Windows)
Classifier: Environment :: Console
Classifier: Natural Language :: Chinese (Simplified)
Classifier: Natural Language :: English
Classifier: Topic :: Software Development :: Documentation
Requires-Python: >=3.9
License-File: LICENSE
Dynamic: license-file
